Metadata-Version: 2.1
Name: pyudcp
Version: 0.5.0
Summary: Python binding for Enigma CLI/ UDCP CLI
Home-page: https://github.com/enigmasys/pyenigma
Author: yogeshvu
Author-email: yogesh.d.barve@vanderbilt.edu
Requires-Python: >=3.7
Requires-Dist: datamodel-code-generator
Requires-Dist: pydantic~=2.4.2
